FlaskBump/__init__.py
FlaskBump/flocked.py
FlaskBump-1.0.0.dist-info/LICENSE
FlaskBump-1.0.0.dist-info/METADATA
FlaskBump-1.0.0.dist-info/WHEEL
FlaskBump-1.0.0.dist-info/top_level.txt
FlaskBump-1.0.0.dist-info/RECORD
