Metadata-Version: 2.1
Name: FlaskBump
Version: 1.0.0
Summary: A simple Flask app that counts the number of requests to it, a visitor count perchance
License:                     GNU GENERAL PUBLIC LICENSE
Project-URL: Homepage, https://github.com/jb2170/FlaskBump/
License-File: LICENSE
Requires-Dist: Flask
